licorice_font/__init__.py
licorice_font/_print_underline.py
licorice_font/_python_string_formatting.py
licorice_font-0.0.3.dist-info/LICENSE
licorice_font-0.0.3.dist-info/METADATA
licorice_font-0.0.3.dist-info/WHEEL
licorice_font-0.0.3.dist-info/top_level.txt
licorice_font-0.0.3.dist-info/RECORD
